find_and_replace/__init__.py
find_and_replace/main.py
find_replace_cli-0.1.1.post3.dist-info/LICENSE
find_replace_cli-0.1.1.post3.dist-info/METADATA
find_replace_cli-0.1.1.post3.dist-info/WHEEL
find_replace_cli-0.1.1.post3.dist-info/entry_points.txt
find_replace_cli-0.1.1.post3.dist-info/RECORD
