Metadata-Version: 2.3
Name: find-replace-cli
Version: 0.1.1.post3
Summary: A command-line tool to find and replace text in files using regex patterns.
Author: Antonio Pisani
Author-email: antonio.pisani@gmail.com
Requires-Python: >=3.10,<4.0
Classifier: Programming Language :: Python :: 3
Classifier: Programming Language :: Python :: 3.10
Classifier: Programming Language :: Python :: 3.11
Classifier: Programming Language :: Python :: 3.12
Classifier: Programming Language :: Python :: 3.13
Project-URL: Documentation, https://find-and-replace.readthedocs.io/
Project-URL: Issue Tracker, https://github.com/apisani1/find-and-replace/issues
Project-URL: Release Notes, https://github.com/apisani1/find-and-replace/releases
Project-URL: Source Code, https://github.com/apisani1/find-and-replace
